CHANGES.rst
MANIFEST.in
README.rst
setup.py
docs/Makefile
docs/source/conf.py
docs/source/config.rst
docs/source/index.rst
docs/source/msg_layout.rst
docs/source/api/cef_plugin.rst
metlog_cef/__init__.py
metlog_cef/cef_plugin.py
metlog_cef.egg-info/PKG-INFO
metlog_cef.egg-info/SOURCES.txt
metlog_cef.egg-info/dependency_links.txt
metlog_cef.egg-info/not-zip-safe
metlog_cef.egg-info/requires.txt
metlog_cef.egg-info/top_level.txt
metlog_cef/tests/__init__.py
metlog_cef/tests/ceftests.py
metlog_cef/tests/test_cef.py