Metadata-Version: 1.0
Name: metlog-cef
Version: 0.2
Summary: CEF extensions to metrics logging
Home-page: https://github.com/mozilla-services/metlog-cef
Author: Victor Ng
Author-email: vng@mozilla.com
License: MPLv2.0
Keywords: metlog metrics logging client
Platform: UNKNOWN
Classifier: License :: OSI Approved :: Mozilla Public License 2.0 (MPL 2.0)
